[
    {
        "pk": 48, 
        "model": "exchange.currency", 
        "fields": {
            "code": "AED", 
            "name": "United Arab Emirates Dirham"
        }
    }, 
    {
        "pk": 64, 
        "model": "exchange.currency", 
        "fields": {
            "code": "AFN", 
            "name": "Afghan Afghani"
        }
    }, 
    {
        "pk": 27, 
        "model": "exchange.currency", 
        "fields": {
            "code": "ALL", 
            "name": "Albanian Lek"
        }
    }, 
    {
        "pk": 57, 
        "model": "exchange.currency", 
        "fields": {
            "code": "AMD", 
            "name": "Armenian Dram"
        }
    }, 
    {
        "pk": 73, 
        "model": "exchange.currency", 
        "fields": {
            "code": "ANG", 
            "name": "Netherlands Antillean Guilder"
        }
    }, 
    {
        "pk": 13, 
        "model": "exchange.currency", 
        "fields": {
            "code": "AOA", 
            "name": "Angolan Kwanza"
        }
    }, 
    {
        "pk": 159, 
        "model": "exchange.currency", 
        "fields": {
            "code": "ARS", 
            "name": "Argentine Peso"
        }
    }, 
    {
        "pk": 102, 
        "model": "exchange.currency", 
        "fields": {
            "code": "AUD", 
            "name": "Australian Dollar"
        }
    }, 
    {
        "pk": 20, 
        "model": "exchange.currency", 
        "fields": {
            "code": "AWG", 
            "name": "Aruban Florin"
        }
    }, 
    {
        "pk": 130, 
        "model": "exchange.currency", 
        "fields": {
            "code": "AZN", 
            "name": "Azerbaijani Manat"
        }
    }, 
    {
        "pk": 137, 
        "model": "exchange.currency", 
        "fields": {
            "code": "BAM", 
            "name": "Bosnia-Herzegovina Convertible Mark"
        }
    }, 
    {
        "pk": 106, 
        "model": "exchange.currency", 
        "fields": {
            "code": "BBD", 
            "name": "Barbadian Dollar"
        }
    }, 
    {
        "pk": 68, 
        "model": "exchange.currency", 
        "fields": {
            "code": "BDT", 
            "name": "Bangladeshi Taka"
        }
    }, 
    {
        "pk": 5, 
        "model": "exchange.currency", 
        "fields": {
            "code": "BGN", 
            "name": "Bulgarian Lev"
        }
    }, 
    {
        "pk": 162, 
        "model": "exchange.currency", 
        "fields": {
            "code": "BHD", 
            "name": "Bahraini Dinar"
        }
    }, 
    {
        "pk": 142, 
        "model": "exchange.currency", 
        "fields": {
            "code": "BIF", 
            "name": "Burundian Franc"
        }
    }, 
    {
        "pk": 54, 
        "model": "exchange.currency", 
        "fields": {
            "code": "BMD", 
            "name": "Bermudan Dollar"
        }
    }, 
    {
        "pk": 34, 
        "model": "exchange.currency", 
        "fields": {
            "code": "BND", 
            "name": "Brunei Dollar"
        }
    }, 
    {
        "pk": 7, 
        "model": "exchange.currency", 
        "fields": {
            "code": "BOB", 
            "name": "Bolivian Boliviano"
        }
    }, 
    {
        "pk": 122, 
        "model": "exchange.currency", 
        "fields": {
            "code": "BRL", 
            "name": "Brazilian Real"
        }
    }, 
    {
        "pk": 98, 
        "model": "exchange.currency", 
        "fields": {
            "code": "BSD", 
            "name": "Bahamian Dollar"
        }
    }, 
    {
        "pk": 82, 
        "model": "exchange.currency", 
        "fields": {
            "code": "BTC", 
            "name": "Bitcoin"
        }
    }, 
    {
        "pk": 83, 
        "model": "exchange.currency", 
        "fields": {
            "code": "BTN", 
            "name": "Bhutanese Ngultrum"
        }
    }, 
    {
        "pk": 9, 
        "model": "exchange.currency", 
        "fields": {
            "code": "BWP", 
            "name": "Botswanan Pula"
        }
    }, 
    {
        "pk": 26, 
        "model": "exchange.currency", 
        "fields": {
            "code": "BYR", 
            "name": "Belarusian Ruble"
        }
    }, 
    {
        "pk": 93, 
        "model": "exchange.currency", 
        "fields": {
            "code": "BZD", 
            "name": "Belize Dollar"
        }
    }, 
    {
        "pk": 139, 
        "model": "exchange.currency", 
        "fields": {
            "code": "CAD", 
            "name": "Canadian Dollar"
        }
    }, 
    {
        "pk": 115, 
        "model": "exchange.currency", 
        "fields": {
            "code": "CDF", 
            "name": "Congolese Franc"
        }
    }, 
    {
        "pk": 24, 
        "model": "exchange.currency", 
        "fields": {
            "code": "CHF", 
            "name": "Swiss Franc"
        }
    }, 
    {
        "pk": 105, 
        "model": "exchange.currency", 
        "fields": {
            "code": "CLF", 
            "name": "Chilean Unit of Account (UF)"
        }
    }, 
    {
        "pk": 112, 
        "model": "exchange.currency", 
        "fields": {
            "code": "CLP", 
            "name": "Chilean Peso"
        }
    }, 
    {
        "pk": 149, 
        "model": "exchange.currency", 
        "fields": {
            "code": "CNY", 
            "name": "Chinese Yuan"
        }
    }, 
    {
        "pk": 84, 
        "model": "exchange.currency", 
        "fields": {
            "code": "COP", 
            "name": "Colombian Peso"
        }
    }, 
    {
        "pk": 47, 
        "model": "exchange.currency", 
        "fields": {
            "code": "CRC", 
            "name": "Costa Rican Col\u00f3n"
        }
    }, 
    {
        "pk": 104, 
        "model": "exchange.currency", 
        "fields": {
            "code": "CUP", 
            "name": "Cuban Peso"
        }
    }, 
    {
        "pk": 140, 
        "model": "exchange.currency", 
        "fields": {
            "code": "CVE", 
            "name": "Cape Verdean Escudo"
        }
    }, 
    {
        "pk": 80, 
        "model": "exchange.currency", 
        "fields": {
            "code": "CZK", 
            "name": "Czech Republic Koruna"
        }
    }, 
    {
        "pk": 30, 
        "model": "exchange.currency", 
        "fields": {
            "code": "DJF", 
            "name": "Djiboutian Franc"
        }
    }, 
    {
        "pk": 8, 
        "model": "exchange.currency", 
        "fields": {
            "code": "DKK", 
            "name": "Danish Krone"
        }
    }, 
    {
        "pk": 95, 
        "model": "exchange.currency", 
        "fields": {
            "code": "DOP", 
            "name": "Dominican Peso"
        }
    }, 
    {
        "pk": 1, 
        "model": "exchange.currency", 
        "fields": {
            "code": "DZD", 
            "name": "Algerian Dinar"
        }
    }, 
    {
        "pk": 49, 
        "model": "exchange.currency", 
        "fields": {
            "code": "EEK", 
            "name": "Estonian Kroon"
        }
    }, 
    {
        "pk": 4, 
        "model": "exchange.currency", 
        "fields": {
            "code": "EGP", 
            "name": "Egyptian Pound"
        }
    }, 
    {
        "pk": 91, 
        "model": "exchange.currency", 
        "fields": {
            "code": "ETB", 
            "name": "Ethiopian Birr"
        }
    }, 
    {
        "pk": 22, 
        "model": "exchange.currency", 
        "fields": {
            "code": "EUR", 
            "name": "Euro"
        }
    }, 
    {
        "pk": 90, 
        "model": "exchange.currency", 
        "fields": {
            "code": "FJD", 
            "name": "Fijian Dollar"
        }
    }, 
    {
        "pk": 155, 
        "model": "exchange.currency", 
        "fields": {
            "code": "FKP", 
            "name": "Falkland Islands Pound"
        }
    }, 
    {
        "pk": 129, 
        "model": "exchange.currency", 
        "fields": {
            "code": "GBP", 
            "name": "British Pound Sterling"
        }
    }, 
    {
        "pk": 62, 
        "model": "exchange.currency", 
        "fields": {
            "code": "GEL", 
            "name": "Georgian Lari"
        }
    }, 
    {
        "pk": 3, 
        "model": "exchange.currency", 
        "fields": {
            "code": "GHS", 
            "name": "Ghanaian Cedi"
        }
    }, 
    {
        "pk": 25, 
        "model": "exchange.currency", 
        "fields": {
            "code": "GIP", 
            "name": "Gibraltar Pound"
        }
    }, 
    {
        "pk": 109, 
        "model": "exchange.currency", 
        "fields": {
            "code": "GMD", 
            "name": "Gambian Dalasi"
        }
    }, 
    {
        "pk": 134, 
        "model": "exchange.currency", 
        "fields": {
            "code": "GNF", 
            "name": "Guinean Franc"
        }
    }, 
    {
        "pk": 111, 
        "model": "exchange.currency", 
        "fields": {
            "code": "GTQ", 
            "name": "Guatemalan Quetzal"
        }
    }, 
    {
        "pk": 152, 
        "model": "exchange.currency", 
        "fields": {
            "code": "GYD", 
            "name": "Guyanaese Dollar"
        }
    }, 
    {
        "pk": 23, 
        "model": "exchange.currency", 
        "fields": {
            "code": "HKD", 
            "name": "Hong Kong Dollar"
        }
    }, 
    {
        "pk": 88, 
        "model": "exchange.currency", 
        "fields": {
            "code": "HNL", 
            "name": "Honduran Lempira"
        }
    }, 
    {
        "pk": 29, 
        "model": "exchange.currency", 
        "fields": {
            "code": "HRK", 
            "name": "Croatian Kuna"
        }
    }, 
    {
        "pk": 70, 
        "model": "exchange.currency", 
        "fields": {
            "code": "HTG", 
            "name": "Haitian Gourde"
        }
    }, 
    {
        "pk": 53, 
        "model": "exchange.currency", 
        "fields": {
            "code": "HUF", 
            "name": "Hungarian Forint"
        }
    }, 
    {
        "pk": 87, 
        "model": "exchange.currency", 
        "fields": {
            "code": "IDR", 
            "name": "Indonesian Rupiah"
        }
    }, 
    {
        "pk": 94, 
        "model": "exchange.currency", 
        "fields": {
            "code": "ILS", 
            "name": "Israeli New Sheqel"
        }
    }, 
    {
        "pk": 78, 
        "model": "exchange.currency", 
        "fields": {
            "code": "INR", 
            "name": "Indian Rupee"
        }
    }, 
    {
        "pk": 136, 
        "model": "exchange.currency", 
        "fields": {
            "code": "IQD", 
            "name": "Iraqi Dinar"
        }
    }, 
    {
        "pk": 148, 
        "model": "exchange.currency", 
        "fields": {
            "code": "IRR", 
            "name": "Iranian Rial"
        }
    }, 
    {
        "pk": 35, 
        "model": "exchange.currency", 
        "fields": {
            "code": "ISK", 
            "name": "Icelandic Kr\u00f3na"
        }
    }, 
    {
        "pk": 101, 
        "model": "exchange.currency", 
        "fields": {
            "code": "JEP", 
            "name": "Jersey Pound"
        }
    }, 
    {
        "pk": 61, 
        "model": "exchange.currency", 
        "fields": {
            "code": "JMD", 
            "name": "Jamaican Dollar"
        }
    }, 
    {
        "pk": 19, 
        "model": "exchange.currency", 
        "fields": {
            "code": "JOD", 
            "name": "Jordanian Dinar"
        }
    }, 
    {
        "pk": 163, 
        "model": "exchange.currency", 
        "fields": {
            "code": "JPY", 
            "name": "Japanese Yen"
        }
    }, 
    {
        "pk": 126, 
        "model": "exchange.currency", 
        "fields": {
            "code": "KES", 
            "name": "Kenyan Shilling"
        }
    }, 
    {
        "pk": 158, 
        "model": "exchange.currency", 
        "fields": {
            "code": "KGS", 
            "name": "Kyrgystani Som"
        }
    }, 
    {
        "pk": 14, 
        "model": "exchange.currency", 
        "fields": {
            "code": "KHR", 
            "name": "Cambodian Riel"
        }
    }, 
    {
        "pk": 107, 
        "model": "exchange.currency", 
        "fields": {
            "code": "KMF", 
            "name": "Comorian Franc"
        }
    }, 
    {
        "pk": 66, 
        "model": "exchange.currency", 
        "fields": {
            "code": "KPW", 
            "name": "North Korean Won"
        }
    }, 
    {
        "pk": 108, 
        "model": "exchange.currency", 
        "fields": {
            "code": "KRW", 
            "name": "South Korean Won"
        }
    }, 
    {
        "pk": 141, 
        "model": "exchange.currency", 
        "fields": {
            "code": "KWD", 
            "name": "Kuwaiti Dinar"
        }
    }, 
    {
        "pk": 16, 
        "model": "exchange.currency", 
        "fields": {
            "code": "KYD", 
            "name": "Cayman Islands Dollar"
        }
    }, 
    {
        "pk": 117, 
        "model": "exchange.currency", 
        "fields": {
            "code": "KZT", 
            "name": "Kazakhstani Tenge"
        }
    }, 
    {
        "pk": 38, 
        "model": "exchange.currency", 
        "fields": {
            "code": "LAK", 
            "name": "Laotian Kip"
        }
    }, 
    {
        "pk": 10, 
        "model": "exchange.currency", 
        "fields": {
            "code": "LBP", 
            "name": "Lebanese Pound"
        }
    }, 
    {
        "pk": 51, 
        "model": "exchange.currency", 
        "fields": {
            "code": "LKR", 
            "name": "Sri Lankan Rupee"
        }
    }, 
    {
        "pk": 74, 
        "model": "exchange.currency", 
        "fields": {
            "code": "LRD", 
            "name": "Liberian Dollar"
        }
    }, 
    {
        "pk": 55, 
        "model": "exchange.currency", 
        "fields": {
            "code": "LSL", 
            "name": "Lesotho Loti"
        }
    }, 
    {
        "pk": 114, 
        "model": "exchange.currency", 
        "fields": {
            "code": "LTL", 
            "name": "Lithuanian Litas"
        }
    }, 
    {
        "pk": 156, 
        "model": "exchange.currency", 
        "fields": {
            "code": "LVL", 
            "name": "Latvian Lats"
        }
    }, 
    {
        "pk": 17, 
        "model": "exchange.currency", 
        "fields": {
            "code": "LYD", 
            "name": "Libyan Dinar"
        }
    }, 
    {
        "pk": 40, 
        "model": "exchange.currency", 
        "fields": {
            "code": "MAD", 
            "name": "Moroccan Dirham"
        }
    }, 
    {
        "pk": 97, 
        "model": "exchange.currency", 
        "fields": {
            "code": "MDL", 
            "name": "Moldovan Leu"
        }
    }, 
    {
        "pk": 72, 
        "model": "exchange.currency", 
        "fields": {
            "code": "MGA", 
            "name": "Malagasy Ariary"
        }
    }, 
    {
        "pk": 128, 
        "model": "exchange.currency", 
        "fields": {
            "code": "MKD", 
            "name": "Macedonian Denar"
        }
    }, 
    {
        "pk": 123, 
        "model": "exchange.currency", 
        "fields": {
            "code": "MMK", 
            "name": "Myanma Kyat"
        }
    }, 
    {
        "pk": 56, 
        "model": "exchange.currency", 
        "fields": {
            "code": "MNT", 
            "name": "Mongolian Tugrik"
        }
    }, 
    {
        "pk": 77, 
        "model": "exchange.currency", 
        "fields": {
            "code": "MOP", 
            "name": "Macanese Pataca"
        }
    }, 
    {
        "pk": 28, 
        "model": "exchange.currency", 
        "fields": {
            "code": "MRO", 
            "name": "Mauritanian Ouguiya"
        }
    }, 
    {
        "pk": 153, 
        "model": "exchange.currency", 
        "fields": {
            "code": "MTL", 
            "name": "Maltese Lira"
        }
    }, 
    {
        "pk": 86, 
        "model": "exchange.currency", 
        "fields": {
            "code": "MUR", 
            "name": "Mauritian Rupee"
        }
    }, 
    {
        "pk": 132, 
        "model": "exchange.currency", 
        "fields": {
            "code": "MVR", 
            "name": "Maldivian Rufiyaa"
        }
    }, 
    {
        "pk": 50, 
        "model": "exchange.currency", 
        "fields": {
            "code": "MWK", 
            "name": "Malawian Kwacha"
        }
    }, 
    {
        "pk": 79, 
        "model": "exchange.currency", 
        "fields": {
            "code": "MXN", 
            "name": "Mexican Peso"
        }
    }, 
    {
        "pk": 15, 
        "model": "exchange.currency", 
        "fields": {
            "code": "MYR", 
            "name": "Malaysian Ringgit"
        }
    }, 
    {
        "pk": 41, 
        "model": "exchange.currency", 
        "fields": {
            "code": "MZN", 
            "name": "Mozambican Metical"
        }
    }, 
    {
        "pk": 2, 
        "model": "exchange.currency", 
        "fields": {
            "code": "NAD", 
            "name": "Namibian Dollar"
        }
    }, 
    {
        "pk": 46, 
        "model": "exchange.currency", 
        "fields": {
            "code": "NGN", 
            "name": "Nigerian Naira"
        }
    }, 
    {
        "pk": 37, 
        "model": "exchange.currency", 
        "fields": {
            "code": "NIO", 
            "name": "Nicaraguan C\u00f3rdoba"
        }
    }, 
    {
        "pk": 76, 
        "model": "exchange.currency", 
        "fields": {
            "code": "NOK", 
            "name": "Norwegian Krone"
        }
    }, 
    {
        "pk": 44, 
        "model": "exchange.currency", 
        "fields": {
            "code": "NPR", 
            "name": "Nepalese Rupee"
        }
    }, 
    {
        "pk": 154, 
        "model": "exchange.currency", 
        "fields": {
            "code": "NZD", 
            "name": "New Zealand Dollar"
        }
    }, 
    {
        "pk": 121, 
        "model": "exchange.currency", 
        "fields": {
            "code": "OMR", 
            "name": "Omani Rial"
        }
    }, 
    {
        "pk": 6, 
        "model": "exchange.currency", 
        "fields": {
            "code": "PAB", 
            "name": "Panamanian Balboa"
        }
    }, 
    {
        "pk": 92, 
        "model": "exchange.currency", 
        "fields": {
            "code": "PEN", 
            "name": "Peruvian Nuevo Sol"
        }
    }, 
    {
        "pk": 143, 
        "model": "exchange.currency", 
        "fields": {
            "code": "PGK", 
            "name": "Papua New Guinean Kina"
        }
    }, 
    {
        "pk": 42, 
        "model": "exchange.currency", 
        "fields": {
            "code": "PHP", 
            "name": "Philippine Peso"
        }
    }, 
    {
        "pk": 52, 
        "model": "exchange.currency", 
        "fields": {
            "code": "PKR", 
            "name": "Pakistani Rupee"
        }
    }, 
    {
        "pk": 124, 
        "model": "exchange.currency", 
        "fields": {
            "code": "PLN", 
            "name": "Polish Zloty"
        }
    }, 
    {
        "pk": 125, 
        "model": "exchange.currency", 
        "fields": {
            "code": "PYG", 
            "name": "Paraguayan Guarani"
        }
    }, 
    {
        "pk": 59, 
        "model": "exchange.currency", 
        "fields": {
            "code": "QAR", 
            "name": "Qatari Rial"
        }
    }, 
    {
        "pk": 160, 
        "model": "exchange.currency", 
        "fields": {
            "code": "RON", 
            "name": "Romanian Leu"
        }
    }, 
    {
        "pk": 161, 
        "model": "exchange.currency", 
        "fields": {
            "code": "RSD", 
            "name": "Serbian Dinar"
        }
    }, 
    {
        "pk": 118, 
        "model": "exchange.currency", 
        "fields": {
            "code": "RUB", 
            "name": "Russian Ruble"
        }
    }, 
    {
        "pk": 75, 
        "model": "exchange.currency", 
        "fields": {
            "code": "RWF", 
            "name": "Rwandan Franc"
        }
    }, 
    {
        "pk": 21, 
        "model": "exchange.currency", 
        "fields": {
            "code": "SAR", 
            "name": "Saudi Riyal"
        }
    }, 
    {
        "pk": 65, 
        "model": "exchange.currency", 
        "fields": {
            "code": "SBD", 
            "name": "Solomon Islands Dollar"
        }
    }, 
    {
        "pk": 138, 
        "model": "exchange.currency", 
        "fields": {
            "code": "SCR", 
            "name": "Seychellois Rupee"
        }
    }, 
    {
        "pk": 164, 
        "model": "exchange.currency", 
        "fields": {
            "code": "SDG", 
            "name": "Sudanese Pound"
        }
    }, 
    {
        "pk": 99, 
        "model": "exchange.currency", 
        "fields": {
            "code": "SEK", 
            "name": "Swedish Krona"
        }
    }, 
    {
        "pk": 145, 
        "model": "exchange.currency", 
        "fields": {
            "code": "SGD", 
            "name": "Singapore Dollar"
        }
    }, 
    {
        "pk": 63, 
        "model": "exchange.currency", 
        "fields": {
            "code": "SHP", 
            "name": "Saint Helena Pound"
        }
    }, 
    {
        "pk": 150, 
        "model": "exchange.currency", 
        "fields": {
            "code": "SLL", 
            "name": "Sierra Leonean Leone"
        }
    }, 
    {
        "pk": 144, 
        "model": "exchange.currency", 
        "fields": {
            "code": "SOS", 
            "name": "Somali Shilling"
        }
    }, 
    {
        "pk": 103, 
        "model": "exchange.currency", 
        "fields": {
            "code": "SRD", 
            "name": "Surinamese Dollar"
        }
    }, 
    {
        "pk": 147, 
        "model": "exchange.currency", 
        "fields": {
            "code": "STD", 
            "name": "S\u00e3o Tom\u00e9 and Pr\u00edncipe Dobra"
        }
    }, 
    {
        "pk": 127, 
        "model": "exchange.currency", 
        "fields": {
            "code": "SVC", 
            "name": "Salvadoran Col\u00f3n"
        }
    }, 
    {
        "pk": 39, 
        "model": "exchange.currency", 
        "fields": {
            "code": "SYP", 
            "name": "Syrian Pound"
        }
    }, 
    {
        "pk": 31, 
        "model": "exchange.currency", 
        "fields": {
            "code": "SZL", 
            "name": "Swazi Lilangeni"
        }
    }, 
    {
        "pk": 32, 
        "model": "exchange.currency", 
        "fields": {
            "code": "THB", 
            "name": "Thai Baht"
        }
    }, 
    {
        "pk": 81, 
        "model": "exchange.currency", 
        "fields": {
            "code": "TJS", 
            "name": "Tajikistani Somoni"
        }
    }, 
    {
        "pk": 85, 
        "model": "exchange.currency", 
        "fields": {
            "code": "TMT", 
            "name": "Turkmenistani Manat"
        }
    }, 
    {
        "pk": 151, 
        "model": "exchange.currency", 
        "fields": {
            "code": "TND", 
            "name": "Tunisian Dinar"
        }
    }, 
    {
        "pk": 131, 
        "model": "exchange.currency", 
        "fields": {
            "code": "TOP", 
            "name": "Tongan Pa\u02bbanga"
        }
    }, 
    {
        "pk": 67, 
        "model": "exchange.currency", 
        "fields": {
            "code": "TRY", 
            "name": "Turkish Lira"
        }
    }, 
    {
        "pk": 120, 
        "model": "exchange.currency", 
        "fields": {
            "code": "TTD", 
            "name": "Trinidad and Tobago Dollar"
        }
    }, 
    {
        "pk": 96, 
        "model": "exchange.currency", 
        "fields": {
            "code": "TWD", 
            "name": "New Taiwan Dollar"
        }
    }, 
    {
        "pk": 11, 
        "model": "exchange.currency", 
        "fields": {
            "code": "TZS", 
            "name": "Tanzanian Shilling"
        }
    }, 
    {
        "pk": 18, 
        "model": "exchange.currency", 
        "fields": {
            "code": "UAH", 
            "name": "Ukrainian Hryvnia"
        }
    }, 
    {
        "pk": 58, 
        "model": "exchange.currency", 
        "fields": {
            "code": "UGX", 
            "name": "Ugandan Shilling"
        }
    }, 
    {
        "pk": 157, 
        "model": "exchange.currency", 
        "fields": {
            "code": "USD", 
            "name": "United States Dollar"
        }
    }, 
    {
        "pk": 36, 
        "model": "exchange.currency", 
        "fields": {
            "code": "UYU", 
            "name": "Uruguayan Peso"
        }
    }, 
    {
        "pk": 146, 
        "model": "exchange.currency", 
        "fields": {
            "code": "UZS", 
            "name": "Uzbekistan Som"
        }
    }, 
    {
        "pk": 110, 
        "model": "exchange.currency", 
        "fields": {
            "code": "VEF", 
            "name": "Venezuelan Bol\u00edvar"
        }
    }, 
    {
        "pk": 12, 
        "model": "exchange.currency", 
        "fields": {
            "code": "VND", 
            "name": "Vietnamese Dong"
        }
    }, 
    {
        "pk": 133, 
        "model": "exchange.currency", 
        "fields": {
            "code": "VUV", 
            "name": "Vanuatu Vatu"
        }
    }, 
    {
        "pk": 135, 
        "model": "exchange.currency", 
        "fields": {
            "code": "WST", 
            "name": "Samoan Tala"
        }
    }, 
    {
        "pk": 33, 
        "model": "exchange.currency", 
        "fields": {
            "code": "XAF", 
            "name": "CFA Franc BEAC"
        }
    }, 
    {
        "pk": 119, 
        "model": "exchange.currency", 
        "fields": {
            "code": "XAG", 
            "name": "Silver (troy ounce)"
        }
    }, 
    {
        "pk": 165, 
        "model": "exchange.currency", 
        "fields": {
            "code": "XAU", 
            "name": "Gold (troy ounce)"
        }
    }, 
    {
        "pk": 116, 
        "model": "exchange.currency", 
        "fields": {
            "code": "XCD", 
            "name": "East Caribbean Dollar"
        }
    }, 
    {
        "pk": 60, 
        "model": "exchange.currency", 
        "fields": {
            "code": "XDR", 
            "name": "Special Drawing Rights"
        }
    }, 
    {
        "pk": 71, 
        "model": "exchange.currency", 
        "fields": {
            "code": "XOF", 
            "name": "CFA Franc BCEAO"
        }
    }, 
    {
        "pk": 89, 
        "model": "exchange.currency", 
        "fields": {
            "code": "XPF", 
            "name": "CFP Franc"
        }
    }, 
    {
        "pk": 69, 
        "model": "exchange.currency", 
        "fields": {
            "code": "YER", 
            "name": "Yemeni Rial"
        }
    }, 
    {
        "pk": 43, 
        "model": "exchange.currency", 
        "fields": {
            "code": "ZAR", 
            "name": "South African Rand"
        }
    }, 
    {
        "pk": 100, 
        "model": "exchange.currency", 
        "fields": {
            "code": "ZMK", 
            "name": "Zambian Kwacha (pre-2013)"
        }
    }, 
    {
        "pk": 113, 
        "model": "exchange.currency", 
        "fields": {
            "code": "ZMW", 
            "name": "Zambian Kwacha"
        }
    }, 
    {
        "pk": 45, 
        "model": "exchange.currency", 
        "fields": {
            "code": "ZWL", 
            "name": "Zimbabwean Dollar"
        }
    }
]